piecemeal/__init__.py
piecemeal/base.py
piecemeal/decorators.py
piecemeal/manager.py
piecemeal/py.typed
test/__init__.py
test/test_plugin.py
test/test_pluginmanager.py
piecemeal-0.9.0.dist-info/LICENSE
piecemeal-0.9.0.dist-info/METADATA
piecemeal-0.9.0.dist-info/WHEEL
piecemeal-0.9.0.dist-info/top_level.txt
piecemeal-0.9.0.dist-info/RECORD
